nadf/__init__.py
nadf/cli/__init__.py
nadf/cli/dots.py
nadf/cli/main.py
nadf/crawler/__init__.py
nadf/crawler/crawler.py
nadf/crawler/http_client/__init__.py
nadf/crawler/http_client/crawler_client.py
nadf/crawler/http_client/httpx_client.py
nadf/crawler/http_client/selenium_client.py
nadf/exception/__init__.py
nadf/exception/base_exception.py
nadf/exception/ssl_invalid_exception.py
nadf/fonts/NotoSerifKR-Bold.ttf
nadf/fonts/NotoSerifKR-Regular.ttf
nadf/parser/__init__.py
nadf/parser/html_parser.py
nadf/parser/html_parser_new.py
nadf/pdf/__init__.py
nadf/pdf/pdf.py
nadf-0.1.34.dist-info/licenses/LICENSE.md
nadf-0.1.34.dist-info/METADATA
nadf-0.1.34.dist-info/WHEEL
nadf-0.1.34.dist-info/entry_points.txt
nadf-0.1.34.dist-info/top_level.txt
nadf-0.1.34.dist-info/RECORD
