Metadata-Version: 2.4
Name: nadf
Version: 0.1.34
Summary: NamuWiki crawler & PDF utilities
Author-email: Donghyeon Park <pdh0128a@gmail.com>
License: MIT
Project-URL: Homepage, https://github.com/pdh0128/nadf
Project-URL: Issues, https://github.com/pdh0128/nadf/issues
Keywords: crawler,namuwiki,pdf
Classifier: Programming Language :: Python :: 3
Classifier: License :: OSI Approved :: MIT License
Classifier: Operating System :: OS Independent
Requires-Python: >=3.10
License-File: LICENSE.md
Requires-Dist: annotated-types==0.7.0
Requires-Dist: anyio==4.10.0
Requires-Dist: beautifulsoup4==4.13.4
Requires-Dist: bs4==0.0.2
Requires-Dist: certifi==2025.8.3
Requires-Dist: charset-normalizer==3.4.3
Requires-Dist: click==8.2.1
Requires-Dist: defusedxml==0.7.1
Requires-Dist: fonttools==4.59.0
Requires-Dist: fpdf2==2.8.4
Requires-Dist: h11==0.16.0
Requires-Dist: httpcore==1.0.9
Requires-Dist: httpx==0.28.1
Requires-Dist: idna==3.10
Requires-Dist: MarkupSafe==3.0.2
Requires-Dist: pdfkit==1.0.0
Requires-Dist: pillow==11.3.0
Requires-Dist: python-multipart==0.0.20
Requires-Dist: requests==2.32.4
Requires-Dist: sniffio==1.3.1
Requires-Dist: soupsieve==2.7
Requires-Dist: starlette==0.47.2
Requires-Dist: typing-inspection==0.4.1
Requires-Dist: typing_extensions==4.14.1
Requires-Dist: urllib3==2.5.0
Requires-Dist: undetected_chromedriver==3.5.5
Requires-Dist: setuptools>=69
Requires-Dist: typer==0.16.0
Dynamic: license-file
